__init__.py
api_view.py
auth.py
csrfExemptAuth.py
exception.py
mapping.py
response.py
response_status.py
router_builder.py
serializers.py
it_drf_utils-0.2.1.dist-info/LICENSE
it_drf_utils-0.2.1.dist-info/METADATA
it_drf_utils-0.2.1.dist-info/WHEEL
it_drf_utils-0.2.1.dist-info/top_level.txt
it_drf_utils-0.2.1.dist-info/RECORD
