Metadata-Version: 2.1
Name: it-drf-utils
Version: 0.2.1
Summary: Django-API-Utils是基于Django编写后端API的一些组件和工具，致力于努力探究 Django 最佳实践。
Author-email: ITStudio <xiaobaitime@qq.com>
Project-URL: Homepage, https://github.com/ITStudioOUC/Django-API-Utils
Project-URL: Bug Tracker, https://github.com/ITStudioOUC/Django-API-Utils/issues
Classifier: Programming Language :: Python :: 3
Classifier: License :: OSI Approved :: MIT License
Classifier: Operating System :: OS Independent
Requires-Python: >=3.2
License-File: LICENSE
